path2dream_processors/__init__.py
path2dream_processors/file_parser.py
path2dream_processors/summary_processor.py
path2dream_processors-0.1.19.dist-info/METADATA
path2dream_processors-0.1.19.dist-info/WHEEL
path2dream_processors-0.1.19.dist-info/top_level.txt
path2dream_processors-0.1.19.dist-info/RECORD
