Metadata-Version: 2.4
Name: path2dream_processors
Version: 0.1.19
Summary: A template for a private Python package
Author-email: Dmitrii Rashchenko <dimitree54@gmail.com>
Project-URL: Homepage, https://github.com/dimitree54/path2dream_processors
Project-URL: Repository, https://github.com/dimitree54/path2dream_processors
Classifier: Programming Language :: Python :: 3
Classifier: License :: OSI Approved :: MIT License
Classifier: Operating System :: OS Independent
Requires-Python: <4.0,>=3.9
Requires-Dist: openai>=1.0.0
Requires-Dist: python-dotenv>=1.0.0
Requires-Dist: llama-parse>=0.4.0
Requires-Dist: nest-asyncio>=1.5.0
Requires-Dist: aiohttp>=3.9.0
Requires-Dist: pydantic>=2.0.0
Requires-Dist: langchain>=0.1.0
Requires-Dist: langchain-openai>=0.1.0
Requires-Dist: langchain-community>=0.0.20
Provides-Extra: dev
Requires-Dist: setuptools>=67.8.0; extra == "dev"
Requires-Dist: bump2version>=1.0.1; extra == "dev"
Requires-Dist: ruff; extra == "dev"
Requires-Dist: twine; extra == "dev"
Requires-Dist: wheel; extra == "dev"
Requires-Dist: pytest>=7.4.0; extra == "dev"
Requires-Dist: pytest-xdist>=3.3.1; extra == "dev"
Requires-Dist: pytest-asyncio>=0.21.0; extra == "dev"
Requires-Dist: aioresponses>=0.7.0; extra == "dev"
Requires-Dist: build; extra == "dev"
